chess/__init__.py
chess/commands.py
chess/cross_correlation.py
chess/get_structures.py
chess/helpers.py
chess/oe.py
chess/sim.py
chess/version.py
chess_hic-0.3.8.data/scripts/chess
chess_hic-0.3.8.dist-info/LICENSE
chess_hic-0.3.8.dist-info/METADATA
chess_hic-0.3.8.dist-info/WHEEL
chess_hic-0.3.8.dist-info/top_level.txt
chess_hic-0.3.8.dist-info/RECORD
