Metadata-Version: 2.1
Name: chess-hic
Version: 0.3.8
Summary: Quantitative comparison and automatic feature extraction for chromatin contact data.
Home-page: https://github.com/vaquerizaslab/chess
Classifier: Programming Language :: Python :: 3
Classifier: License :: OSI Approved :: MIT License
Classifier: Operating System :: OS Independent
License-File: LICENSE
Requires-Dist: cython
Requires-Dist: numpy (>=1.8.0)
Requires-Dist: fanc (>=0.9.9)
Requires-Dist: scikit-image
Requires-Dist: future
Requires-Dist: pathos
Requires-Dist: pandas (>=1.1.3)
Requires-Dist: scipy
Requires-Dist: intervaltree
Requires-Dist: pybedtools
Requires-Dist: tqdm
Requires-Dist: kneed
